pfex
