Metadata-Version: 2.1
Name: pfex
Version: 0.1.13
Summary: Package for fast and accurate calculation of Fisher Exact Test with Enrichr library support.
Home-page: https://github.com/maayanlab/pfex
Author: Alexander Lachmann
Author-email: alexander.lachmann@mssm.edu
Classifier: Programming Language :: Python :: 3
Classifier: License :: OSI Approved :: Apache Software License
Classifier: Operating System :: OS Independent
Requires-Python: >=3.6
License-File: LICENSE
